__init__.py
main.py
csv2vcd-0.1.0.dist-info/licenses/LICENCE
csv2vcd-0.1.0.dist-info/METADATA
csv2vcd-0.1.0.dist-info/WHEEL
csv2vcd-0.1.0.dist-info/entry_points.txt
csv2vcd-0.1.0.dist-info/top_level.txt
csv2vcd-0.1.0.dist-info/RECORD
