Metadata-Version: 2.4
Name: csv2vcd
Version: 0.1.0
Summary: Convert CSV files to VCD (Value Change Dump) format for digital waveform visualization
Author-email: SystemVII <thaw-skid-fossil@duck.com>
License: MIT
Project-URL: Homepage, https://github.com/SystemVll/csv2vcd
Project-URL: Bug Tracker, https://github.com/SystemVll/csv2vcd/issues
Classifier: Programming Language :: Python :: 3
Classifier: License :: OSI Approved :: MIT License
Classifier: Operating System :: OS Independent
Requires-Python: >=3.7
License-File: LICENCE
Dynamic: license-file
